cams_ilvo_utils/__init__.py
cams_ilvo_utils/calib/__init__.py
cams_ilvo_utils/calib/board.py
cams_ilvo_utils/calib/calibration.py
cams_ilvo_utils/calib/process.py
cams_ilvo_utils/img/__init__.py
cams_ilvo_utils/img/image.py
cams_ilvo_utils/img/transform.py
test/__init__.py
test/test_calib_files.py
test/test_camera_projection.py
test/test_image.py
cams_ilvo_utils-0.0.1.dist-info/LICENCE
cams_ilvo_utils-0.0.1.dist-info/METADATA
cams_ilvo_utils-0.0.1.dist-info/WHEEL
cams_ilvo_utils-0.0.1.dist-info/top_level.txt
cams_ilvo_utils-0.0.1.dist-info/RECORD
