Metadata-Version: 2.2
Name: cams_ilvo_utils
Version: 0.0.1
Summary: The camera ILVO utils
Author-email: Axel Willekens <axel.willekens@ilvo.vlaanderen.be>
Classifier: Programming Language :: Python :: 3
Classifier: Operating System :: OS Independent
Requires-Python: >=3.9
License-File: LICENCE
Requires-Dist: numpy>=2.0.0
Requires-Dist: opencv-python>=4.8.0.74
